odoo10_addon_account_check_printing_report_dlt103-10.0.1.0.0-py2.7-nspkg.pth
odoo/addons/account_check_printing_report_dlt103/README.rst
odoo/addons/account_check_printing_report_dlt103/__init__.py
odoo/addons/account_check_printing_report_dlt103/__manifest__.py
odoo/addons/account_check_printing_report_dlt103/data/account_payment_check_report_data.xml
odoo/addons/account_check_printing_report_dlt103/data/report_paperformat.xml
odoo/addons/account_check_printing_report_dlt103/data/report_paperformat_parameter.xml
odoo/addons/account_check_printing_report_dlt103/report/__init__.py
odoo/addons/account_check_printing_report_dlt103/report/account_check_writing_report.xml
odoo/addons/account_check_printing_report_dlt103/report/check_print.py
odoo/addons/account_check_printing_report_dlt103/views/report_check.xml
odoo10_addon_account_check_printing_report_dlt103-10.0.1.0.0.dist-info/DESCRIPTION.rst
odoo10_addon_account_check_printing_report_dlt103-10.0.1.0.0.dist-info/METADATA
odoo10_addon_account_check_printing_report_dlt103-10.0.1.0.0.dist-info/RECORD
odoo10_addon_account_check_printing_report_dlt103-10.0.1.0.0.dist-info/WHEEL
odoo10_addon_account_check_printing_report_dlt103-10.0.1.0.0.dist-info/metadata.json
odoo10_addon_account_check_printing_report_dlt103-10.0.1.0.0.dist-info/namespace_packages.txt
odoo10_addon_account_check_printing_report_dlt103-10.0.1.0.0.dist-info/top_level.txt
